openapi_pydantic_v2/__init__.py
openapi_pydantic_v2/py.typed
openapi_pydantic_v2/util.py
openapi_pydantic_v2/v3/__init__.py
openapi_pydantic_v2/v3/v3_0_3/README.md
openapi_pydantic_v2/v3/v3_0_3/__init__.py
openapi_pydantic_v2/v3/v3_0_3/callback.py
openapi_pydantic_v2/v3/v3_0_3/components.py
openapi_pydantic_v2/v3/v3_0_3/contact.py
openapi_pydantic_v2/v3/v3_0_3/discriminator.py
openapi_pydantic_v2/v3/v3_0_3/encoding.py
openapi_pydantic_v2/v3/v3_0_3/example.py
openapi_pydantic_v2/v3/v3_0_3/external_documentation.py
openapi_pydantic_v2/v3/v3_0_3/header.py
openapi_pydantic_v2/v3/v3_0_3/info.py
openapi_pydantic_v2/v3/v3_0_3/license.py
openapi_pydantic_v2/v3/v3_0_3/link.py
openapi_pydantic_v2/v3/v3_0_3/media_type.py
openapi_pydantic_v2/v3/v3_0_3/oauth_flow.py
openapi_pydantic_v2/v3/v3_0_3/oauth_flows.py
openapi_pydantic_v2/v3/v3_0_3/open_api.py
openapi_pydantic_v2/v3/v3_0_3/operation.py
openapi_pydantic_v2/v3/v3_0_3/parameter.py
openapi_pydantic_v2/v3/v3_0_3/path_item.py
openapi_pydantic_v2/v3/v3_0_3/paths.py
openapi_pydantic_v2/v3/v3_0_3/reference.py
openapi_pydantic_v2/v3/v3_0_3/request_body.py
openapi_pydantic_v2/v3/v3_0_3/response.py
openapi_pydantic_v2/v3/v3_0_3/responses.py
openapi_pydantic_v2/v3/v3_0_3/schema.py
openapi_pydantic_v2/v3/v3_0_3/security_requirement.py
openapi_pydantic_v2/v3/v3_0_3/security_scheme.py
openapi_pydantic_v2/v3/v3_0_3/server.py
openapi_pydantic_v2/v3/v3_0_3/server_variable.py
openapi_pydantic_v2/v3/v3_0_3/tag.py
openapi_pydantic_v2/v3/v3_0_3/util.py
openapi_pydantic_v2/v3/v3_0_3/xml.py
openapi_pydantic_v2/v3/v3_1_0/README.md
openapi_pydantic_v2/v3/v3_1_0/__init__.py
openapi_pydantic_v2/v3/v3_1_0/callback.py
openapi_pydantic_v2/v3/v3_1_0/components.py
openapi_pydantic_v2/v3/v3_1_0/contact.py
openapi_pydantic_v2/v3/v3_1_0/discriminator.py
openapi_pydantic_v2/v3/v3_1_0/encoding.py
openapi_pydantic_v2/v3/v3_1_0/example.py
openapi_pydantic_v2/v3/v3_1_0/external_documentation.py
openapi_pydantic_v2/v3/v3_1_0/header.py
openapi_pydantic_v2-0.1.1.dist-info/LICENSE
openapi_pydantic_v2-0.1.1.dist-info/WHEEL
openapi_pydantic_v2-0.1.1.dist-info/METADATA
openapi_pydantic_v2-0.1.1.dist-info/RECORD
